blindscrambler/__init__.py
blindscrambler/_core.abi3.so
blindscrambler/_core.pyi
blindscrambler/deepl/__init__.py
blindscrambler/deepl/two_layer_binary_classification.py
blindscrambler/differential/__init__.py
blindscrambler/differential/discrete.py
blindscrambler/distributions/__init__.py
blindscrambler/distributions/cvdistributions.py
blindscrambler/matrix/__init__.py
blindscrambler/matrix/elementary.py
blindscrambler/model/__init__.py
blindscrambler/model/logit.py
blindscrambler/model/neuralnet.py
blindscrambler/model/regression.py
blindscrambler/py.typed
blindscrambler-0.1.15.dist-info/METADATA
blindscrambler-0.1.15.dist-info/WHEEL
blindscrambler-0.1.15.dist-info/RECORD
