Metadata-Version: 2.4
Name: blindscrambler
Version: 0.1.15
Requires-Dist: matplotlib>=3.10.6
Requires-Dist: numpy>=2.3.3
Requires-Dist: onnx>=1.19.1
Requires-Dist: polars>=1.34.0
Requires-Dist: scikit-learn>=1.7.2
Requires-Dist: scipy>=1.16.2
Requires-Dist: torch>=2.8.0
Requires-Dist: torcheval>=0.0.7
Requires-Dist: twine>=6.1.0
Summary: Add your description here
Author-email: blindscramblergh <blindscrambler@gmail.com>
Requires-Python: >=3.12
